setup.py
nphusl/__init__.py
nphusl/_nphusl_cython.c
nphusl/_nphusl_expr.py
nphusl/constants.py
nphusl/nphusl.py
nphusl.egg-info/PKG-INFO
nphusl.egg-info/SOURCES.txt
nphusl.egg-info/dependency_links.txt
nphusl.egg-info/not-zip-safe
nphusl.egg-info/requires.txt
nphusl.egg-info/top_level.txt