Metadata-Version: 1.1
Name: nphusl
Version: 1.4.1
Summary: A HUSL color space conversion library that works with numpy
Home-page: https://github.com/TadLeonard/husl-numpy
Author: Tad Leonard
Author-email: tadfleonard@gmail.com
License: MIT
Download-URL: https://github.com/TadLeonard/husl-numpy/archive/1.4.1.tar.gz
Keywords: husl hsl color conversion rgb image processing
Platform: UNKNOWN
Classifier: Development Status :: 5 - Production/Stable
Classifier: Intended Audience :: Developers
Classifier: Operating System :: OS Independent
Classifier: Programming Language :: Python :: 3
Classifier: Programming Language :: Python :: 3 :: Only
Classifier: Intended Audience :: Science/Research
Classifier: Topic :: Multimedia
Classifier: Topic :: Multimedia :: Graphics
